jdMacroPlayer/Constants.py
jdMacroPlayer/Environment.py
jdMacroPlayer/Functions.py
jdMacroPlayer/Icon.png
jdMacroPlayer/Version.txt
jdMacroPlayer/__init__.py
jdMacroPlayer/core/Action.py
jdMacroPlayer/core/ActionTypeTests.py
jdMacroPlayer/core/Languages.py
jdMacroPlayer/core/Macro.py
jdMacroPlayer/core/MacroManager.py
jdMacroPlayer/core/Settings.py
jdMacroPlayer/core/__init__.py
jdMacroPlayer/core/action_types/ActionTypeBase.py
jdMacroPlayer/core/action_types/ActionTypeClick.py
jdMacroPlayer/core/action_types/ActionTypeCommand.py
jdMacroPlayer/core/action_types/ActionTypeKeypress.py
jdMacroPlayer/core/action_types/ActionTypeMousemove.py
jdMacroPlayer/core/action_types/ActionTypeNotification.py
jdMacroPlayer/core/action_types/ActionTypeSleep.py
jdMacroPlayer/core/action_types/ActionTypeType.py
jdMacroPlayer/core/action_types/__init__.py
jdMacroPlayer/daemon/Daemon.py
jdMacroPlayer/daemon/Interface.xml
jdMacroPlayer/daemon/__init__.py
jdMacroPlayer/daemon/__main__.py
jdMacroPlayer/data/changelog.html
jdMacroPlayer/data/jdmacroplayer-ydotool.rule
jdMacroPlayer/data/keycodes.json
jdMacroPlayer/data/translators.json
jdMacroPlayer/data/welcome.html
jdMacroPlayer/gui/AboutDialog.py
jdMacroPlayer/gui/AddEditActionDialog.py
jdMacroPlayer/gui/AddEditMacroDialog.py
jdMacroPlayer/gui/MainWindow.py
jdMacroPlayer/gui/SettingsDialog.py
jdMacroPlayer/gui/WelcomeDialog.py
jdMacroPlayer/gui/__init__.py
jdMacroPlayer/shared/KeylistWidget.py
jdMacroPlayer/shared/SelectKeyDialog.py
jdMacroPlayer/shared/__init__.py
jdMacroPlayer/translations/jdMacroPlayer_da.qm
jdMacroPlayer/translations/jdMacroPlayer_de.qm
jdMacroPlayer/translations/jdMacroPlayer_nl.qm
jdMacroPlayer/translations/jdMacroPlayer_pl.qm
jdMacroPlayer/translations/jdMacroPlayer_ru.qm
jdMacroPlayer/ui/AboutDialog.ui
jdMacroPlayer/ui/AddEditActionDialog.ui
jdMacroPlayer/ui/AddEditMacroDialog.ui
jdMacroPlayer/ui/MainWindow.ui
jdMacroPlayer/ui/SelectKeyDialog.ui
jdMacroPlayer/ui/SettingsDialog.ui
jdMacroPlayer-0.2.dist-info/LICENSE
jdMacroPlayer-0.2.dist-info/METADATA
jdMacroPlayer-0.2.dist-info/WHEEL
jdMacroPlayer-0.2.dist-info/entry_points.txt
jdMacroPlayer-0.2.dist-info/top_level.txt
jdMacroPlayer-0.2.dist-info/RECORD
