Metadata-Version: 2.1
Name: jdMacroPlayer
Version: 0.2
Summary: Wayland compatible macro player for Linux
Author-email: JakobDev <jakobdev@gmx.de>
License: GPL-3
Project-URL: Source, https://codeberg.org/JakobDev/jdMacroPlayer
Project-URL: Issues, https://codeberg.org/JakobDev/jdMacroPlayer/issues
Project-URL: Translate, https://translate.codeberg.org/projects/jdMacroPlayer
Project-URL: Donation, https://ko-fi.com/jakobdev
Keywords: JakobDev,Linux,Macro
Classifier: Development Status :: 5 - Production/Stable
Classifier: Intended Audience :: Developers
Classifier: Environment :: Other Environment
Classifier: License :: OSI Approved :: GNU General Public License v3 (GPLv3)
Classifier: Operating System :: POSIX
Classifier: Operating System :: POSIX :: BSD
Classifier: Operating System :: POSIX :: Linux
Classifier: Programming Language :: Python :: 3
Classifier: Programming Language :: Python :: 3.10
Classifier: Programming Language :: Python :: 3.11
Classifier: Programming Language :: Python :: 3 :: Only
Classifier: Programming Language :: Python :: Implementation :: CPython
Requires-Python: >=3.10
License-File: LICENSE
Requires-Dist: PyQt6
Requires-Dist: jeepney
Provides-Extra: set-process-name
Requires-Dist: setproctitle ; extra == 'set-process-name'
